README.rst
setup.py
iso639/__init__.py
iso639/iso-639-3-macrolanguages.tab
iso639/iso-639-3.tab
iso639/iso-639-3_Name_Index.tab
iso639/iso-639-3_Retirements.tab
iso639/iso639-1.tsv
iso639/iso639-2.tsv
iso639/iso639-5.tsv
iso639/iso639.py
iso_639.egg-info/PKG-INFO
iso_639.egg-info/SOURCES.txt
iso_639.egg-info/dependency_links.txt
iso_639.egg-info/entry_points.txt
iso_639.egg-info/not-zip-safe
iso_639.egg-info/top_level.txt